.VERSION
AUTHORS.rst
CONTRIBUTING.rst
HISTORY.rst
LICENSE
MANIFEST.in
Pipfile
Pipfile.lock
README.rst
USAGE.rst
dev-requirements.txt
requirements.txt
setup.cfg
setup.py
docs/Makefile
docs/authors.rst
docs/conf.py
docs/contributing.rst
docs/history.rst
docs/index.rst
docs/installation.rst
docs/modules.rst
docs/ovchipcardlib.rst
docs/readme.rst
docs/usage.rst
ovchipcardlib/.VERSION
ovchipcardlib/AUTHORS.rst
ovchipcardlib/CONTRIBUTING.rst
ovchipcardlib/HISTORY.rst
ovchipcardlib/LICENSE
ovchipcardlib/Pipfile
ovchipcardlib/Pipfile.lock
ovchipcardlib/README.rst
ovchipcardlib/USAGE.rst
ovchipcardlib/__init__.py
ovchipcardlib/_version.py
ovchipcardlib/dev-requirements.txt
ovchipcardlib/helpers.py
ovchipcardlib/ovchipcardlib.py
ovchipcardlib/ovchipcardlibexceptions.py
ovchipcardlib/requirements.txt
ovchipcardlib.egg-info/PKG-INFO
ovchipcardlib.egg-info/SOURCES.txt
ovchipcardlib.egg-info/dependency_links.txt
ovchipcardlib.egg-info/not-zip-safe
ovchipcardlib.egg-info/requires.txt
ovchipcardlib.egg-info/top_level.txt