Metadata-Version: 2.1
Name: ovchipcardlib
Version: 0.1.1
Summary: A library to interact with ov-chip cards on line api. 
Home-page: https://github.com/costastf/ovchipcardlib
Author: Costas Tyfoxylos
Author-email: costas.tyf@gmail.com
License: MIT
Keywords: ovchipcardlib OV-Chip
Platform: UNKNOWN
Classifier: Development Status :: 4 - Beta
Classifier: Intended Audience :: Developers
Classifier: License :: OSI Approved :: MIT License
Classifier: Natural Language :: English
Classifier: Programming Language :: Python :: 3.7
License-File: LICENSE
License-File: AUTHORS.rst
